Workbook

Sheet Hướng dẫn
A1: AFG POS – QA/QC PHASE 2 TESTCASE DESIGN | 25/10/2026
A3: Mục | B3: Nội dung
A4: Mục đích | B4: 71 testcase thiết kế cho Pha 2 Sprint 3–4 (26/10–20/11/2026), không phải kết quả thực thi.
A5: Nguồn thứ tự | B5: BRD In Scope + các BR-QR/BR-MT/BR-SB/BR-TT; POS Rollout Board mục Đối chiếu phạm vi BRD; Git BE api-catalog mục D; OpenAPI main.
A6: Phân biệt contract | B6: OpenAPI main và catalog A7 xác nhận một số GET/Pha 1; catalog D ghi 📝 đề xuất. Không gọi 404 của route đề xuất là business Failed.
A7: Trạng thái ban đầu | B7: Tất cả Test Cases = Not Executed, Actual Result/Run Date/Evidence trống. Chỉ chuyển Passed khi chạy trên SHA và fixture cụ thể.
A8: Quy tắc Expected | B8: Các rule BRD có ID giữ nguyên. Payload/HTTP chưa định nghĩa ghi TBD/RFI; không tự bịa mã lỗi hoặc số điểm.
A9: Cách sử dụng | B9: RFI & Gaps → BE/PO chốt contract và fixture → cập nhật API Scope → chạy case cô lập → Execution Log → Dashboard.
A10: An toàn dữ liệu | B10: Chỉ staging/QA fixture. Không lưu JWT, PIN, PAN/CVV, SĐT thật, payment provider secret vào workbook hoặc Git.
A11: Phạm vi có thể retest ngay | B11: GET /api/v1/audit-logs và các endpoint Pha 1 phụ trợ chỉ là readiness/regression; /pay mô phỏng không chứng minh CARD/QR/CASH.
A12: Phạm vi Pha 3 | B12: Combo/menu full/versioning, ERP/E-invoice thực, offline sync stub không gộp vào Pha 2 trừ khi PO đổi scope.
A13: Baseline | B13: Git main api-catalog sha 597dd8e3; OpenAPI sha 65a264a4 (file snapshots). Chưa đối chiếu staging runtime 25/10.

Sheet Test Cases
A1: AFG POS – PHASE 2 TEST CASES | 71 thiết kế, 0 business execution
A2: Pha 2 Sprint 3–4 | Contract Pha 2 chưa triển khai trong OpenAPI snapshot; mọi Actual/Status chỉ cập nhật từ run thật.
A3: TC ID | B3: Tiêu đề Test Case | C3: Module | D3: Priority | E3: Severity | F3: Loại Test | G3: Preconditions (Điều kiện tiên quyết) | H3: Test Steps (Các bước thực hiện) | I3: Test Data (Dữ liệu đầu vào) | J3: Expected Result (Kết quả mong đợi) | K3: Actual Result (Kết quả thực tế) | L3: Status | M3: Ngày thực hiện | N3: Người thực hiện | O3: Req ID | P3: Automation? | Q3: Ghi chú | R3: Method + Endpoint | S3: Postman Ref | T3: Nguồn / Version | U3: Contract / RFI
A4: P2-PAY-001 | B4: Thanh toán CASH đủ số tiền | C4: Payment Processing | D4: Critical | E4: Critical | F4: Positive | G4: Staging/QA cô lập; order có các món SERVED, chưa thanh toán; test gateway sandbox và role được cấp. | H4: 1. Xác minh SHA/role/fixture cô lập. 2. Gửi CASH đúng tổng bill; đọc lại payments/order/table. 3. Đọc lại order/session/ledger/audit và đối chiếu expected; dọn fixture thuộc QA. | I4: amount=total; method=CASH | J4: Một giao dịch được ghi, tổng đã trả khớp bill; trạng thái order/bàn chuyển đúng contract; audit có actor/thời điểm; HTTP/payload TBD khi route đề xuất. | L4: Not Executed | O4: BRD Payment Processing; Board Pha 2 | P4: Có – sau contract & fixture | Q4: Design only; Đề xuất Pha 2. Không suy PASS từ preflight. | R4: POST /orders/{id}/payments | S4: Chưa có Postman Pha 2 | T4: SRC-BRD; SRC-BOARD; SRC-CATALOG; SRC-OPENAPI (main snapshot) | U4: Contract: Đề xuất Pha 2; RFI: P2-RFI-PAY
A5: P2-PAY-002 | B5: Thanh toán CARD qua sandbox thành công | C5: Payment Processing | D5: Critical | E5: Critical | F5: Integration | G5: Staging/QA cô lập; order có các món SERVED, chưa thanh toán; test gateway sandbox và role được cấp. | H5: 1. Xác minh SHA/role/fixture cô lập. 2. Tạo CARD payment và nhận kết quả sandbox thành công. 3. Đọc lại order/session/ledger/audit và đối chiếu expected; dọn fixture thuộc QA. | I5: tokenized card sandbox | J5: Chỉ xác nhận PAID sau callback hợp lệ; không lưu PAN/CVV; giao dịch truy vết được; HTTP/payload TBD khi route đề xuất. | L5: Not Executed | O5: BRD Payment Processing | P5: Có – sau contract & fixture | Q5: Design only; Đề xuất Pha 2. Không suy PASS từ preflight. | R5: POST /orders/{id}/payments | S5: Chưa có Postman Pha 2 | T5: SRC-BRD; SRC-BOARD; SRC-CATALOG; SRC-OPENAPI (main snapshot) | U5: Contract: Đề xuất Pha 2; RFI: P2-RFI-PAY
A6: P2-PAY-003 | B6: Thanh toán QR Pay qua sandbox thành công | C6: Payment Processing | D6: Critical | E6: Critical | F6: Integration | G6: Staging/QA cô lập; order có các món SERVED, chưa thanh toán; test gateway sandbox và role được cấp. | H6: 1. Xác minh SHA/role/fixture cô lập. 2. Tạo QR payment; xác nhận callback hợp lệ. 3. Đọc lại order/session/ledger/audit và đối chiếu expected; dọn fixture thuộc QA. | I6: provider sandbox transaction | J6: Không đóng bill trước xác nhận; sau xác nhận ghi đúng amount, provider reference và audit; HTTP/payload TBD khi route đề xuất. | L6: Not Executed | O6: BRD Payment Processing | P6: Có – sau contract & fixture | Q6: Design only; Đề xuất Pha 2. Không suy PASS từ preflight. | R6: POST /orders/{id}/payments | S6: Chưa có Postman Pha 2 | T6: SRC-BRD; SRC-BOARD; SRC-CATALOG; SRC-OPENAPI (main snapshot) | U6: Contract: Đề xuất Pha 2; RFI: P2-RFI-PAY
A7: P2-PAY-004 | B7: Gateway trả thất bại và cho phép thử lại | C7: Payment Processing | D7: Critical | E7: Critical | F7: Negative | G7: Staging/QA cô lập; order có các món SERVED, chưa thanh toán; test gateway sandbox và role được cấp. | H7: 1. Xác minh SHA/role/fixture cô lập. 2. Mô phỏng failed callback rồi retry bằng giao dịch mới. 3. Đọc lại order/session/ledger/audit và đối chiếu expected; dọn fixture thuộc QA. | I7: failed callback + retry | J7: Bill còn unpaid, không ghi PAID giả; retry không nhân đôi số tiền; HTTP/payload TBD khi route đề xuất. | L7: Not Executed | O7: BRD Payment failure recovery | P7: Có – sau contract & fixture | Q7: Design only; Đề xuất Pha 2. Không suy PASS từ preflight. | R7: POST /orders/{id}/payments | S7: Chưa có Postman Pha 2 | T7: SRC-BRD; SRC-BOARD; SRC-CATALOG; SRC-OPENAPI (main snapshot) | U7: Contract: Đề xuất Pha 2; RFI: P2-RFI-PAY
A8: P2-PAY-005 | B8: Callback lặp không tạo thanh toán trùng | C8: Payment Processing | D8: Critical | E8: Critical | F8: Idempotency | G8: Staging/QA cô lập; order có các món SERVED, chưa thanh toán; test gateway sandbox và role được cấp. | H8: 1. Xác minh SHA/role/fixture cô lập. 2. Gửi hai callback giống nhau có chữ ký hợp lệ. 3. Đọc lại order/session/ledger/audit và đối chiếu expected; dọn fixture thuộc QA. | I8: same provider event ID | J8: Một payment/transition duy nhất; các lần lặp được nhận diện idempotent; HTTP/payload TBD khi route đề xuất. | L8: Not Executed | O8: BRD Payment confirmation; Data Consistency | P8: Có – sau contract & fixture | Q8: Design only; Đề xuất Pha 2. Không suy PASS từ preflight. | R8: POST /payments/webhooks/{provider} | S8: Chưa có Postman Pha 2 | T8: SRC-BRD; SRC-BOARD; SRC-CATALOG; SRC-OPENAPI (main snapshot) | U8: Contract: Đề xuất Pha 2; RFI: P2-RFI-PAY
A9: P2-PAY-006 | B9: Callback sai chữ ký bị từ chối | C9: Payment Processing | D9: Critical | E9: Critical | F9: Security | G9: Staging/QA cô lập; order có các món SERVED, chưa thanh toán; test gateway sandbox và role được cấp. | H9: 1. Xác minh SHA/role/fixture cô lập. 2. Gửi callback sai chữ ký/tamper amount. 3. Đọc lại order/session/ledger/audit và đối chiếu expected; dọn fixture thuộc QA. | I9: signature invalid | J9: Không ghi payment, không đổi order/table; sự kiện được log an toàn; HTTP/payload TBD khi route đề xuất. | L9: Not Executed | O9: BRD Payment Security | P9: Có – sau contract & fixture | Q9: Design only; Đề xuất Pha 2. Không suy PASS từ preflight. | R9: POST /payments/webhooks/{provider} | S9: Chưa có Postman Pha 2 | T9: SRC-BRD; SRC-BOARD; SRC-CATALOG; SRC-OPENAPI (main snapshot) | U9: Contract: Đề xuất Pha 2; RFI: P2-RFI-PAY
A10: P2-PAY-007 | B10: Thiếu số tiền hoặc phương thức không hợp lệ | C10: Payment Processing | D10: High | E10: High | F10: Validation | G10: Staging/QA cô lập; order có các món SERVED, chưa thanh toán; test gateway sandbox và role được cấp. | H10: 1. Xác minh SHA/role/fixture cô lập. 2. Gửi thiếu amount, amount ≤ 0, hoặc method ngoài danh mục. 3. Đọc lại order/session/ledger/audit và đối chiếu expected; dọn fixture thuộc QA. | I10: amount=0; method=UNKNOWN | J10: Request bị từ chối theo mã lỗi contract; không có payment mới; HTTP/payload TBD khi route đề xuất. | L10: Not Executed | O10: BRD Payment Processing | P10: Có – sau contract & fixture | Q10: Design only; Đề xuất Pha 2. Không suy PASS từ preflight. | R10: POST /orders/{id}/payments | S10: Chưa có Postman Pha 2 | T10: SRC-BRD; SRC-BOARD; SRC-CATALOG; SRC-OPENAPI (main snapshot) | U10: Contract: Đề xuất Pha 2; RFI: P2-RFI-PAY
A11: P2-PAY-008 | B11: Split bill tổng bằng bill gốc | C11: Payment Processing | D11: Critical | E11: Critical | F11: Positive | G11: Staging/QA cô lập; order có các món SERVED, chưa thanh toán; test gateway sandbox và role được cấp. | H11: 1. Xác minh SHA/role/fixture cô lập. 2. Tách theo món/số tiền theo luật đã chốt, thanh toán từng phần. 3. Đọc lại order/session/ledger/audit và đối chiếu expected; dọn fixture thuộc QA. | I11: hai nhóm món; discount/fee | J11: Các phần tổng hợp khớp bill gốc, tax/discount/fee phân bổ đúng; bàn chưa đóng khi còn unpaid; HTTP/payload TBD khi route đề xuất. | L11: Not Executed | O11: BR-SB-003/004/005/006/009 | P11: Có – sau contract & fixture | Q11: Design only; Đề xuất Pha 2. Không suy PASS từ preflight. | R11: POST /orders/{id}/split-bill | S11: Chưa có Postman Pha 2 | T11: SRC-BRD; SRC-BOARD; SRC-CATALOG; SRC-OPENAPI (main snapshot) | U11: Contract: Đề xuất Pha 2; RFI: P2-RFI-SPLIT
A12: P2-PAY-009 | B12: Không chuyển món đã trả sang bill khác | C12: Payment Processing | D12: High | E12: High | F12: Negative | G12: Staging/QA cô lập; order có các món SERVED, chưa thanh toán; test gateway sandbox và role được cấp. | H12: 1. Xác minh SHA/role/fixture cô lập. 2. Thanh toán một bill con rồi thử chuyển món đã trả. 3. Đọc lại order/session/ledger/audit và đối chiếu expected; dọn fixture thuộc QA. | I12: một split đã PAID | J12: Chặn thay đổi, phần đã trả và audit giữ nguyên; HTTP/payload TBD khi route đề xuất. | L12: Not Executed | O12: BR-SB-002/008 | P12: Có – sau contract & fixture | Q12: Design only; Đề xuất Pha 2. Không suy PASS từ preflight. | R12: POST /orders/{id}/split-bill | S12: Chưa có Postman Pha 2 | T12: SRC-BRD; SRC-BOARD; SRC-CATALOG; SRC-OPENAPI (main snapshot) | U12: Contract: Đề xuất Pha 2; RFI: P2-RFI-SPLIT
A13: P2-PAY-010 | B13: Bấm xác nhận split hai lần | C13: Payment Processing | D13: High | E13: High | F13: Concurrency | G13: Staging/QA cô lập; order có các món SERVED, chưa thanh toán; test gateway sandbox và role được cấp. | H13: 1. Xác minh SHA/role/fixture cô lập. 2. Gửi cùng request/key lặp trong 3 giây. 3. Đọc lại order/session/ledger/audit và đối chiếu expected; dọn fixture thuộc QA. | I13: same key / double tap | J13: Không tạo thêm bill con; audit không nhân đôi business action; HTTP/payload TBD khi route đề xuất. | L13: Not Executed | O13: BR-SB-010/011 | P13: Có – sau contract & fixture | Q13: Design only; Đề xuất Pha 2. Không suy PASS từ preflight. | R13: POST /orders/{id}/split-bill | S13: Chưa có Postman Pha 2 | T13: SRC-BRD; SRC-BOARD; SRC-CATALOG; SRC-OPENAPI (main snapshot) | U13: Contract: Đề xuất Pha 2; RFI: P2-RFI-SPLIT
A14: P2-PAY-011 | B14: Cashier và Supervisor được thanh toán, Waiter bị chặn | C14: Payment Processing | D14: Critical | E14: Critical | F14: RBAC | G14: Staging/QA cô lập; order có các món SERVED, chưa thanh toán; test gateway sandbox và role được cấp. | H14: 1. Xác minh SHA/role/fixture cô lập. 2. Gửi cùng business action với ba role, mỗi lượt fixture riêng. 3. Đọc lại order/session/ledger/audit và đối chiếu expected; dọn fixture thuộc QA. | I14: CASHIER/SUPERVISOR/WAITER | J14: Role hợp lệ được xử lý; role không hợp lệ không đổi dữ liệu; xác nhận lại mâu thuẫn Customer trong matrix; HTTP/payload TBD khi route đề xuất. | L14: Not Executed | O14: BRD Permission Matrix: Process Payment; catalog Pha 1 /pay | P14: Có – sau contract & fixture | Q14: Design only; Đề xuất Pha 2. Không suy PASS từ preflight. | R14: POST /orders/{id}/payments | S14: Chưa có Postman Pha 2 | T14: SRC-BRD; SRC-BOARD; SRC-CATALOG; SRC-OPENAPI (main snapshot) | U14: Contract: Đề xuất Pha 2; RFI: P2-RFI-ROLE
A15: P2-TBL-001 | B15: Transfer giữ nguyên session/order/ticket | C15: Table Management nâng cao | D15: Critical | E15: Critical | F15: Positive | G15: Hai bàn QA riêng trong cùng outlet; session/order/ticket có ID và trạng thái đã chụp trước thao tác. | H15: 1. Xác minh SHA/role/fixture cô lập. 2. Chuyển session từ bàn OCCUPIED sang bàn AVAILABLE cùng outlet. 3. Đọc lại order/session/ledger/audit và đối chiếu expected; dọn fixture thuộc QA. | I15: QA fixture cô lập | J15: Giữ session ID, order/ticket; bàn nguồn AVAILABLE, đích OCCUPIED; audit có actor/time; HTTP/payload TBD khi route đề xuất. | L15: Not Executed | O15: BR-TT-001/002/004/005/010/011 | P15: Có – sau contract & fixture | Q15: Design only; Đề xuất Pha 2. Không suy PASS từ preflight. | R15: POST /tables/{id}/transfer | S15: Chưa có Postman Pha 2 | T15: SRC-BRD; SRC-BOARD; SRC-CATALOG; SRC-OPENAPI (main snapshot) | U15: Contract: Đề xuất Pha 2; RFI: P2-RFI-TABLE
... A74: P2-ORD-003 | B74: Void món đang nấu yêu cầu PIN Supervisor | C74: Order Control Pha 2 | D74: Critical | E74: Critical | F74: Security | G74: Order QA cô lập; trạng thái/version và quyền Supervisor được xác minh trước thao tác. | H74: 1. Xác minh SHA/role/fixture cô lập. 2. Thử PIN đúng/sai/thiếu bằng Supervisor, cùng reason. 3. Đọc lại order/session/ledger/audit và đối chiếu expected; dọn fixture thuộc QA. | I74: QA fixture cô lập | J74: Chỉ PIN hợp lệ mới VOID/CANCELLED; ghi audit, policy lockout chờ PO/BE; HTTP/payload TBD khi route đề xuất. | L74: Not Executed | O74: S2-RFI-09; SEC-02 Pha 2 | P74: Có – sau contract & fixture | Q74: Design only; Đề xuất Pha 2. Không suy PASS từ preflight. | R74: POST /orders/{id}/items/{item_id}/void + PIN [TBD] | S74: Chưa có Postman Pha 2 | T74: SRC-BRD; SRC-BOARD; SRC-CATALOG; SRC-OPENAPI (main snapshot) | U74: Contract: Đề xuất Pha 2; RFI: P2-RFI-PIN

Sheet API Scope
A1: PHASE 2 – BRD ↔ BE API SCOPE & CONTRACT GATE
A2: “Đề xuất” trong api-catalog mục D là thiết kế tương lai; không được đánh dấu “Staging/Passed”.
A3: API Scope ID | B3: Nhóm BRD | C3: Phạm vi | D3: Method + Endpoint | E3: Contract state | F3: Nguồn BRD | G3: RFI | H3: Mức độ | I3: Fixture cần | J3: QA next step | K3: Ghi chú | L3: Số TC | M3: TC Passed | N3: TC chưa Passed | O3: Nguồn API
A4: P2 Payment | B4: Payment Processing | C4: Thanh toán CASH/CARD/QR, callback, thất bại, split bill | D4: POST /orders/{id}/payments; GET /orders/{id}/payments; POST /payments/{id}/cancel; POST /payments/webhooks/{provider}; POST /orders/{id}/split-bill | E4: Đề xuất Pha 2 | F4: BRD Payment Processing; Board Pha 2; catalog D | G4: P2-RFI-PAY; P2-RFI-SPLIT | H4: P0/P1 | I4: Isolated QA data; roles; sandbox | J4: BE cung cấp OpenAPI mới, sample payload/error; QA cập nhật Expected rồi mới chạy | K4: Snapshot main không là runtime staging | L4: =COUNTIF('Test Cases'!$C$4:$C$74,B4) -> 11 | M4: =COUNTIFS('Test Cases'!$C$4:$C$74,B4,'Test Cases'!$L$4:$L$74,"Passed") -> 0 | N4: =L4-M4 -> 11 | O4: docs/api/api-catalog.md §D; docs/api/openapi.json
A5: P2 Table | B5: Table Management nâng cao | C5: Transfer/Merge/Split; giữ order, KDS, QR, audit | D5: POST /tables/{id}/transfer; POST /tables/merge; POST /orders/{id}/split | E5: Đề xuất Pha 2 | F5: BR-TT, BR-MT, BR-SB; catalog D | G5: P2-RFI-TABLE | H5: P0/P1 | I5: Isolated QA data; roles; sandbox | J5: BE cung cấp OpenAPI mới, sample payload/error; QA cập nhật Expected rồi mới chạy | K5: Snapshot main không là runtime staging | L5: =COUNTIF('Test Cases'!$C$4:$C$74,B5) -> 12 | M5: =COUNTIFS('Test Cases'!$C$4:$C$74,B5,'Test Cases'!$L$4:$L$74,"Passed") -> 0 | N5: =L5-M5 -> 12 | O5: docs/api/api-catalog.md §D; docs/api/openapi.json
A6: P2 Permission | B6: User & Permission | C6: Staff CRUD/lock/unlock/reset; PIN/refresh; matrix | D6: GET/POST /staff; PATCH /staff/{id}; /lock; /unlock; /reset-password; POST /auth/pin-login; /refresh | E6: Đề xuất Pha 2 | F6: BRD User & Permission; catalog D | G6: P2-RFI-ROLE; P2-RFI-PIN | H6: P0/P1 | I6: Isolated QA data; roles; sandbox | J6: BE cung cấp OpenAPI mới, sample payload/error; QA cập nhật Expected rồi mới chạy | K6: Snapshot main không là runtime staging | L6: =COUNTIF('Test Cases'!$C$4:$C$74,B6) -> 9 | M6: =COUNTIFS('Test Cases'!$C$4:$C$74,B6,'Test Cases'!$L$4:$L$74,"Passed") -> 0 | N6: =L6-M6 -> 9 | O6: docs/api/api-catalog.md §D; docs/api/openapi.json
A7: P2 Audit | B7: Audit Search / Report | C7: Audit search/filter hiện có; export/report đề xuất | D7: GET /api/v1/audit-logs; GET /audit-logs/export [TBD] | E7: Pha 1 GET có; export đề xuất | F7: BRD Audit & Logging; catalog A7/D | G7: P2-RFI-AUD | H7: P0/P1 | I7: Isolated QA data; roles; sandbox | J7: BE cung cấp OpenAPI mới, sample payload/error; QA cập nhật Expected rồi mới chạy | K7: Snapshot main không là runtime staging | L7: =COUNTIF('Test Cases'!$C$4:$C$74,B7) -> 5 | M7: =COUNTIFS('Test Cases'!$C$4:$C$74,B7,'Test Cases'!$L$4:$L$74,"Passed") -> 0 | N7: =L7-M7 -> 5 | O7: docs/api/api-catalog.md §D; docs/api/openapi.json
A8: P2 QR | B8: QR Ordering | C8: Token công khai, menu/cart/order, bill, modifier | D8: POST /tables/{id}/qr-session; GET /public/qr/{token}/menu; POST /public/qr/{token}/orders; GET /public/qr/{token}/orders/{id}; POST /public/qr/{token}/request-bill | E8: Đề xuất Pha 2 | F8: BR-QR-001..010; catalog D | G8: P2-RFI-QR; P2-RFI-MOD | H8: P0/P1 | I8: Isolated QA data; roles; sandbox | J8: BE cung cấp OpenAPI mới, sample payload/error; QA cập nhật Expected rồi mới chạy | K8: Snapshot main không là runtime staging | L8: =COUNTIF('Test Cases'!$C$4:$C$74,B8) -> 15 | M8: =COUNTIFS('Test Cases'!$C$4:$C$74,B8,'Test Cases'!$L$4:$L$74,"Passed") -> 0 | N8: =L8-M8 -> 15 | O8: docs/api/api-catalog.md §D; docs/api/openapi.json
A9: P2 Rewards | B9: Rewards System | C9: Customer, điểm, eligibility, apply/remove, ledger | D9: GET/POST /customers; GET /customers/{id}/rewards; POST /orders/{id}/apply-reward; DELETE /orders/{id}/rewards/{reward_id} | E9: Đề xuất Pha 2 | F9: BRD Rewards; catalog D | G9: P2-RFI-RWD | H9: P0/P1 | I9: Isolated QA data; roles; sandbox | J9: BE cung cấp OpenAPI mới, sample payload/error; QA cập nhật Expected rồi mới chạy | K9: Snapshot main không là runtime staging | L9: =COUNTIF('Test Cases'!$C$4:$C$74,B9) -> 11 | M9: =COUNTIFS('Test Cases'!$C$4:$C$74,B9,'Test Cases'!$L$4:$L$74,"Passed") -> 0 | N9: =L9-M9 -> 11 | O9: docs/api/api-catalog.md §D; docs/api/openapi.json
A10: P2 Monitoring | B10: System Control & Monitoring | C10: Sentry staging, permission hardening, basic perf | D10: Sentry staging; /health; /ready; /version | E10: Giám sát đề xuất; health có | F10: BRD Monitoring; Board Pha 2 | G10: P2-RFI-MON; P2-RFI-PERF | H10: P0/P1 | I10: Isolated QA data; roles; sandbox | J10: BE cung cấp OpenAPI mới, sample payload/error; QA cập nhật Expected rồi mới chạy | K10: Snapshot main không là runtime staging | L10: =COUNTIF('Test Cases'!$C$4:$C$74,B10) -> 5 | M10: =COUNTIFS('Test Cases'!$C$4:$C$74,B10,'Test Cases'!$L$4:$L$74,"Passed") -> 0 | N10: =L10-M10 -> 5 | O10: docs/api/api-catalog.md §D; docs/api/openapi.json
A11: P2 Order Control | B11: Order Control Pha 2 | C11: Expected-version và PIN Void theo RFI Sprint 2 | D11: Order write expected_version [TBD]; POST /orders/{id}/items/{item_id}/void + PIN [TBD] | E11: Đề xuất Pha 2 | F11: BE phản hồi S2-RFI-02/09 ngày 22/10 | G11: P2-RFI-VER; P2-RFI-PIN | H11: P0/P1 | I11: Isolated QA data; roles; sandbox | J11: BE cung cấp OpenAPI mới, sample payload/error; QA cập nhật Expected rồi mới chạy | K11: Snapshot main không là runtime staging | L11: =COUNTIF('Test Cases'!$C$4:$C$74,B11) -> 3 | M11: =COUNTIFS('Test Cases'!$C$4:$C$74,B11,'Test Cases'!$L$4:$L$74,"Passed") -> 0 | N11: =L11-M11 -> 3 | O11: docs/api/api-catalog.md §D; docs/api/openapi.json

Sheet Dashboard
A1: AFG POS | PHASE 2 QA DESIGN DASHBOARD
A2: Thiết kế sẵn ≠ business PASS. Mọi testcase còn Not Executed và phụ thuộc contract/fixture của BE/PO.
A3: Chỉ số | B3: Giá trị | C3: Điều kiện | D3: Nhóm | E3: Thực trạng API | F3: Hành động
A4: Tổng testcase | B4: =COUNTA('Test Cases'!A4:A74) -> 71 | C4: 8 nhóm BRD | D4: Payment/Table/User/Audit/QR/Rewards/Monitoring/Order Control | E4: Đối chiếu catalog D | F4: RFI từng nhóm
A5: Passed | B5: =COUNTIF('Test Cases'!L4:L74,"Passed") -> 0 | C5: Chỉ từ Execution Log | D5: Không có lượt Phase 2 | E5: 0 từ thiết kế | F5: Không suy từ Pha 1
A6: Not Executed | B6: =COUNTIF('Test Cases'!L4:L74,"Not Executed") -> 71 | C6: Design only | D6: API đề xuất | E6: Chưa có run | F6: Chốt contract/fixture
A7: Blocked | B7: =COUNTIF('Test Cases'!L4:L74,"Blocked") -> 0 | C7: Chỉ khi có blocker thực thi | D7: TBD | E7: Không tự gán Failed | F7: Ghi blocker + owner
A8: Failed | B8: =COUNTIF('Test Cases'!L4:L74,"Failed") -> 0 | C8: Chỉ có run và expected đã chốt | D8: TBD | E8: Không có | F8: Lập defect nếu tái hiện
A9: Coverage business | B9: =IFERROR(B5/B4,0) -> 0 | C9: Passed/total; không dùng làm “80%” | D9: 0% khi chưa run | E9: Không có business Phase2 | F9: Chờ BE/PO

Sheet Execution Log
A1: PHASE 2 EXECUTION LOG – CHỈ GHI RUN THỰC TẾ
A2: Chưa chạy business Phase 2. Mỗi run: SHA runtime trước/sau, QA fixture, cleanup và evidence; không lưu secret.
A3: Run ID | B3: Run Date | C3: Environment | D3: Build / SHA | E3: Tool | F3: Test Ref | G3: Action | H3: Expected HTTP | I3: Actual HTTP | J3: Result | K3: Evidence | L3: Tester | M3: Note

Sheet RFI & Gaps
A1: PHASE 2 – OPEN RFI / GAPS / OWNER
A3: ID | B3: Loại | C3: Vấn đề / quyết định cần chốt | D3: Nguồn A | E3: Nguồn B / Quan sát | F3: Tác động QA | G3: Quyết định tạm thời | H3: Owner | I3: Status | J3: TC liên quan | K3: Nguồn / Trace | L3: Ngày chốt | M3: Ghi chú
A4: P2-RFI-PAY | B4: Payment | C4: Gateway/sandbox, CASH/CARD/QR payload, callback signature, failure/UNKNOWN, amount & error codes | D4: BRD / POS Rollout Board | E4: BE api-catalog §D; OpenAPI main snapshot | F4: Expected/HTTP/fixture chưa đủ để business test | G4: Design only; không đánh PASS | H4: PO + BE + Finance | I4: Open | J4: P2-PAY-001; P2-PAY-002; P2-PAY-003; P2-PAY-004; P2-PAY-005; P2-PAY-006; P2-PAY-007 | K4: SRC-BRD; SRC-BOARD; SRC-CATALOG; SRC-OPENAPI | M4: Không gán HTTP/PAID cho flow chưa có contract
A5: P2-RFI-SPLIT | B5: Split Bill | C5: Split theo món/khách/amount/% và quy tắc tax, fee, discount, partial pay | D5: BRD / POS Rollout Board | E5: BE api-catalog §D; OpenAPI main snapshot | F5: Expected/HTTP/fixture chưa đủ để business test | G5: Design only; không đánh PASS | H5: PO + BE | I5: Open | J5: P2-PAY-008; P2-PAY-009; P2-PAY-010 | K5: SRC-BRD; SRC-BOARD; SRC-CATALOG; SRC-OPENAPI | M5: BR-SB có rule nhưng endpoint/payload chưa chốt
A6: P2-RFI-TABLE | B6: Advanced Table | C6: Transfer/Merge/Split route, master_session, conflict/retry, role, capacity, offline | D6: BRD / POS Rollout Board | E6: BE api-catalog §D; OpenAPI main snapshot | F6: Expected/HTTP/fixture chưa đủ để business test | G6: Design only; không đánh PASS | H6: PO + BE | I6: Open | J6: P2-TBL-001; P2-TBL-002; P2-TBL-003; P2-TBL-004; P2-TBL-005; P2-TBL-006; P2-TBL-007; P2-TBL-008; P2-TBL-009; P2-TBL-010; P2-TBL-011; P2-TBL-012 | K6: SRC-BRD; SRC-BOARD; SRC-CATALOG; SRC-OPENAPI | M6: BR-TT/BR-MT có rule; catalog D chỉ đề xuất
A7: P2-RFI-ROLE | B7: RBAC | C7: Permission Matrix BRD mâu thuẫn current API (Create Order POS Waiter, Process Payment Customer, table action Customer); token invalidation | D7: BRD / POS Rollout Board | E7: BE api-catalog §D; OpenAPI main snapshot | F7: Expected/HTTP/fixture chưa đủ để business test | G7: Design only; không đánh PASS | H7: PO + BE + Security | I7: Open | J7: P2-PAY-011; P2-USR-001; P2-USR-002; P2-USR-003; P2-USR-004; P2-USR-005; P2-USR-007; P2-USR-008; P2-USR-009; P2-MON-005 | K7: SRC-BRD; SRC-BOARD; SRC-CATALOG; SRC-OPENAPI | M7: Chốt từng role/action trước expected HTTP
A8: P2-RFI-PIN | B8: PIN/Lockout | C8: PIN Void và pin-login, N lần sai, cooldown, reset/recovery | D8: BRD / POS Rollout Board | E8: BE api-catalog §D; OpenAPI main snapshot | F8: Expected/HTTP/fixture chưa đủ để business test | G8: Design only; không đánh PASS | H8: PO + BE + Security | I8: Open | J8: P2-USR-006; P2-ORD-003 | K8: SRC-BRD; SRC-BOARD; SRC-CATALOG; SRC-OPENAPI | M8: BE phản hồi 22/10: Pha 2, chưa contract
A9: P2-RFI-AUD | B9: Audit report | C9: Export path/format, sort/pagination, retention, immutable proof, PII | D9: BRD / POS Rollout Board | E9: BE api-catalog §D; OpenAPI main snapshot | F9: Expected/HTTP/fixture chưa đủ để business test | G9: Design only; không đánh PASS | H9: BE + PO | I9: Open | J9: P2-AUD-001; P2-AUD-002; P2-AUD-003; P2-AUD-004; P2-AUD-005 | K9: SRC-BRD; SRC-BOARD; SRC-CATALOG; SRC-OPENAPI | M9: GET audit đã có, export chưa
A10: P2-RFI-QR | B10: QR Token & Security | C10: Issuer, TTL/revoke, rate limit, token/table binding, send mode, request bill | D10: BRD / POS Rollout Board | E10: BE api-catalog §D; OpenAPI main snapshot | F10: Expected/HTTP/fixture chưa đủ để business test | G10: Design only; không đánh PASS | H10: PO + BE + Security | I10: Open | J10: P2-QR-001; P2-QR-002; P2-QR-003; P2-QR-004; P2-QR-005; P2-QR-006; P2-QR-007; P2-QR-008; P2-QR-009; P2-QR-010; P2-QR-013; P2-QR-014 | K10: SRC-BRD; SRC-BOARD; SRC-CATALOG; SRC-OPENAPI | M10: BR-QR có rule; public endpoint chưa code
A11: P2-RFI-MOD | B11: Modifier | C11: Schema, price, station split, availability, POS/QR consistency | D11: BRD / POS Rollout Board | E11: BE api-catalog §D; OpenAPI main snapshot | F11: Expected/HTTP/fixture chưa đủ để business test | G11: Design only; không đánh PASS | H11: PO + BE | I11: Open | J11: P2-QR-011; P2-QR-012 | K11: SRC-BRD; SRC-BOARD; SRC-CATALOG; SRC-OPENAPI | M11: Menu đầy đủ Pha 3 nhưng modifier cơ bản xếp Pha 2; cần chốt ranh giới
A12: P2-RFI-RWD | B12: Rewards | C12: Earn/redeem ratio, expiry, eligibility, cap, reversal/refund, PII, per-outlet | D12: BRD / POS Rollout Board | E12: BE api-catalog §D; OpenAPI main snapshot | F12: Expected/HTTP/fixture chưa đủ để business test | G12: Design only; không đánh PASS | H12: PO + BE | I12: Open | J12: P2-RWD-001; P2-RWD-002; P2-RWD-003; P2-RWD-004; P2-RWD-005; P2-RWD-006; P2-RWD-007; P2-RWD-008; P2-RWD-009; P2-RWD-010; P2-RWD-011 | K12: SRC-BRD; SRC-BOARD; SRC-CATALOG; SRC-OPENAPI | M12: BRD phần chi tiết Rewards còn trống
A13: P2-RFI-MON | B13: Monitoring | C13: Sentry DSN staging, alert thresholds/owner, redaction, retention | D13: BRD / POS Rollout Board | E13: BE api-catalog §D; OpenAPI main snapshot | F13: Expected/HTTP/fixture chưa đủ để business test | G13: Design only; không đánh PASS | H13: BE + PO | I13: Open | J13: P2-MON-001; P2-MON-002; P2-MON-003; P2-MON-004 | K13: SRC-BRD; SRC-BOARD; SRC-CATALOG; SRC-OPENAPI | M13: Không gửi lỗi thật/secret khi test
A14: P2-RFI-PERF | B14: Performance | C14: QR ≤30s: start/end và môi trường đo; sync ≤2s; payment timeout 3s | D14: BRD / POS Rollout Board | E14: BE api-catalog §D; OpenAPI main snapshot | F14: Expected/HTTP/fixture chưa đủ để business test | G14: Design only; không đánh PASS | H14: PO + QA + BE | I14: Open | J14: P2-QR-015 | K14: SRC-BRD; SRC-BOARD; SRC-CATALOG; SRC-OPENAPI | M14: Không kết luận chỉ từ unit/preflight
A15: P2-RFI-VER | B15: Version Conflict | C15: expected_version ở write nào, 409 shape/current_version, retry with key | D15: BRD / POS Rollout Board | E15: BE api-catalog §D; OpenAPI main snapshot | F15: Expected/HTTP/fixture chưa đủ để business test | G15: Design only; không đánh PASS | H15: PO + BE | I15: Open | J15: P2-ORD-001; P2-ORD-002 | K15: SRC-BRD; SRC-BOARD; SRC-CATALOG; SRC-OPENAPI | M15: BE 22/10: Pha 2 nếu SRS bắt buộc
A16: P2-RFI-SCOPE | B16: Phạm vi Phase 2 | C16: E-invoice/ERP và Menu full Pha 3, offline stub; QR/Rewards Pha 2 | D16: BRD / POS Rollout Board | E16: BE api-catalog §D; OpenAPI main snapshot | F16: Expected/HTTP/fixture chưa đủ để business test | G16: Design only; không đánh PASS | H16: PO | I16: Open | K16: SRC-BRD; SRC-BOARD; SRC-CATALOG; SRC-OPENAPI | M16: Không kéo tính năng Pha 3 vào Passed Pha 2

Sheet Nguồn & Version
A1: SOURCE BASELINE – PHASE 2 TEST DESIGN
A2: Mã nguồn | B2: Tên nguồn | C2: Phiên bản / thời điểm | D2: Nhóm | E2: URL / File | F2: Mức độ | G2: Lưu ý
A3: SRC-BRD | B3: Pos System BRD(2).docx | C3: Library user upload 18/10/2026 | D3: Requirement | E3: Pos System BRD(2).docx | F3: Primary | G3: BR-QR-001..010, BR-MT-001..014, BR-SB-001..014, BR-TT-001..014; Payment/Rewards detail còn ô trống
A4: SRC-BOARD | B4: POS Rollout Board – Đối chiếu phạm vi BRD | C4: Claude artifact, đọc 25/10/2026 | D4: Roadmap | E4: https://claude.ai/artifact/DX5FYqW11NpTxJkcqHY3H3 | F4: Planning | G4: Pha 2 Sprint 3–4: Payment, Table advanced, User/Permission, Audit report, QR, Rewards, Sentry
A5: SRC-CATALOG | B5: BE API Catalog §A7/§D | C5: Git main sha 597dd8e3ef8648c48a0cab32ce97e102550dabf2 | D5: BE Proposal | E5: https://github.com/Mouse-hybrid/DU-AN-THUC-TAP/blob/main/docs/api/api-catalog.md | F5: Proposal + existing | G5: §D đánh dấu API Pha 2–3 là đề xuất, không coi như đã deploy
A6: SRC-OPENAPI | B6: BE OpenAPI main | C6: Git main sha 65a264a489f857ca0ef289b8af73dc772fdbef56 | D6: BE Contract | E6: https://github.com/Mouse-hybrid/DU-AN-THUC-TAP/blob/main/docs/api/openapi.json | F6: Snapshot contract | G6: Không có nhóm public QR/Rewards/payment methods/table advanced; chưa kiểm runtime staging
A7: SRC-BE-RFI | B7: BE phản hồi Sprint 2 RFI | C7: 22/10/2026; người dùng cung cấp | D7: Decision provisional | E7: S2-RFI-02/09/10 (hội thoại QA) | F7: Pending PO | G7: Expected_version, PIN Void, transfer/merge/split chuyển Pha 2; cần contract cụ thể
A8: SRC-TPL | B8: AFG_POS_QAQC_116_phase1_2026-10-22_updated.xlsx | C8: User Library 22/10/2026 | D8: QA template | E8: AFG_POS_QAQC_116_phase1_2026-10-22_updated.xlsx | F8: Format | G8: Giữ 21 cột Test Cases, 13 cột Execution Log, RFI/API Scope/Dashboard

Sheet Test Data & Roles
A1: PHASE 2 FIXTURE & ROLE PLAN – KHÔNG LƯU SECRET
A2: Loại | B2: Dữ liệu / Vai trò | C2: Nguồn | D2: Điều kiện mở | E2: Cleanup / Rủi ro
A3: Environment | B3: Staging, khóa SHA trước/sau | C3: GET /version | D3: BE xác nhận build Phase2 | E3: Không dùng production hay reset toàn bộ
A4: Accounts | B4: SUPERVISOR, CASHIER, WAITER, KITCHEN, QR public | C4: BRD Permission Matrix + seed | D4: BE cấp QA role matrix & outlet | E4: Không ghi JWT/PIN/password
A5: Tables | B5: 2–3 bàn QA AVAILABLE + isolated sessions | C5: BE seed / ownership | D5: Owner và fixture book lịch test | E5: Chỉ cleanup phiên thuộc QA
A6: Payment | B6: Gateway sandbox CASH/CARD/QR; success/fail/duplicate callbacks | C6: BE + provider | D6: Ký test credentials & callback sandbox | E6: Không dùng thẻ/tiền thật
A7: QR | B7: QR token theo table/session, TTL/revoke, menu modifier | C7: BE Phase2 | D7: Token fixture và abuse guard | E7: Hủy token/QA order sau run
A8: Rewards | B8: Customer QA, phone giả, ledger/reward đủ và thiếu | C8: PO + BE | D8: Luật earn/redeem/cap/refund | E8: Không dùng SĐT thật; đảo QA points
A9: Audit/Monitoring | B9: Synthetic QA action/error & correlation ID | C9: BE/Sentry staging | D9: Quyền đọc và redaction policy | E9: Không gửi secret vào telemetry
A10: Concurrency | B10: 2 clients/keys trên cùng QA entity | C10: QA | D10: Barrier/script và expected_version | E10: Không dùng entity người khác
